xia_module_cosmos_gh_gcp/__init__.py
xia_module_cosmos_gh_gcp/cosmos.py
xia_module_cosmos_gh_gcp/templates/ghgcp-module-cosmos/base/main.tf
xia_module_cosmos_gh_gcp/templates/ghgcp-module-cosmos/example/landscape.yaml
xia_module_cosmos_gh_gcp/templates/ghgcp-module-cosmos/module/locals.tf
xia_module_cosmos_gh_gcp/templates/ghgcp-module-cosmos/module/main.tf
xia_module_cosmos_gh_gcp/templates/ghgcp-module-cosmos/module/output.tf
xia_module_cosmos_gh_gcp/templates/ghgcp-module-cosmos/module/variables.tf
xia_module_cosmos_gh_gcp-0.0.1.dist-info/LICENSE
xia_module_cosmos_gh_gcp-0.0.1.dist-info/METADATA
xia_module_cosmos_gh_gcp-0.0.1.dist-info/WHEEL
xia_module_cosmos_gh_gcp-0.0.1.dist-info/top_level.txt
xia_module_cosmos_gh_gcp-0.0.1.dist-info/RECORD
