Metadata-Version: 2.1
Name: xia-module-cosmos-gh-gcp
Version: 0.0.1
Requires-Python: >=3.9
License-File: LICENSE
Requires-Dist: PyYAML
